{"nodes": [{"id": "classdiagram_2on5edug_beiqath8", "label": "classDiagram-2ON5EDUG-BeiqAtH8.js", "file_type": "code", "source_file": "dist/public/assets/classDiagram-2ON5EDUG-BeiqAtH8.js", "source_location": "L1"}, {"id": "classdiagram_2on5edug_beiqath8_db", "label": "db()", "file_type": "code", "source_file": "dist/public/assets/classDiagram-2ON5EDUG-BeiqAtH8.js", "source_location": "L1"}], "edges": [{"source": "classdiagram_2on5edug_beiqath8", "target": "chunk_b4bg7prw_bvmqogki_js", "relation": "imports_from", "confidence": "EXTRACTED", "source_file": "dist/public/assets/classDiagram-2ON5EDUG-BeiqAtH8.js", "source_location": "L1", "weight": 1.0}, {"source": "classdiagram_2on5edug_beiqath8", "target": "mermaid_core_bfqjixun_js", "relation": "imports_from", "confidence": "EXTRACTED", "source_file": "dist/public/assets/classDiagram-2ON5EDUG-BeiqAtH8.js", "source_location": "L1", "weight": 1.0}, {"source": "classdiagram_2on5edug_beiqath8", "target": "chunk_fmbd7uc4_azj7fnjy_js", "relation": "imports_from", "confidence": "EXTRACTED", "source_file": "dist/public/assets/classDiagram-2ON5EDUG-BeiqAtH8.js", "source_location": "L1", "weight": 1.0}, {"source": "classdiagram_2on5edug_beiqath8", "target": "chunk_55iaceb6_3atyyqqs_js", "relation": "imports_from", "confidence": "EXTRACTED", "source_file": "dist/public/assets/classDiagram-2ON5EDUG-BeiqAtH8.js", "source_location": "L1", "weight": 1.0}, {"source": "classdiagram_2on5edug_beiqath8", "target": "chunk_qn33pnhl_cajzgi_t_js", "relation": "imports_from", "confidence": "EXTRACTED", "source_file": "dist/public/assets/classDiagram-2ON5EDUG-BeiqAtH8.js", "source_location": "L1", "weight": 1.0}, {"source": "classdiagram_2on5edug_beiqath8", "target": "index_zjsxhyjg_js", "relation": "imports_from", "confidence": "EXTRACTED", "source_file": "dist/public/assets/classDiagram-2ON5EDUG-BeiqAtH8.js", "source_location": "L1", "weight": 1.0}, {"source": "classdiagram_2on5edug_beiqath8", "target": "classdiagram_2on5edug_beiqath8_db", "relation": "contains", "confidence": "EXTRACTED", "source_file": "dist/public/assets/classDiagram-2ON5EDUG-BeiqAtH8.js", "source_location": "L1", "weight": 1.0}]}